vhcs/__init__.py
vhcs/ext/__init__.py
vhcs/ext/daas/__init__.py
vhcs/ext/daas/av_helper.py
vhcs/ext/daas/cidr_util.py
vhcs/ext/daas/default_orders.py
vhcs/ext/daas/helper.py
vhcs/ext/daas/infra.py
vhcs/ext/daas/infra_green.py
vhcs/ext/daas/infra_reuse.py
vhcs/ext/daas/order.py
vhcs/ext/daas/order_util.py
vhcs/ext/daas/template.py
vhcs/ext/daas/tenant_prep.py
vhcs/ext/daas/tenant_summary.py
vhcs/ext/daas/templates/__init__.py
vhcs/ext/daas/templates/v1/__init__.py
vhcs/ext/daas/templates/v1/infra-green.blueprint.yml
vhcs/ext/daas/templates/v1/infra-green.var.yml
vhcs/ext/daas/templates/v1/infra-reuse.blueprint.yml
vhcs/ext/daas/templates/v1/infra-reuse.var.yml
vhcs/ext/daas/templates/v1/tenant-order.var.yml
vhcs/ext/daas/templates/v1/tenant.blueprint.yml
vhcs/ext/daas/templates/v1/tenant.var.yml
hcs_cli_ext_daas-0.1.175.dist-info/METADATA
hcs_cli_ext_daas-0.1.175.dist-info/WHEEL
hcs_cli_ext_daas-0.1.175.dist-info/top_level.txt
hcs_cli_ext_daas-0.1.175.dist-info/RECORD
